Metadata-Version: 2.1
Name: flowpm
Version: 0.1.1
Summary: Particle Mesh Simulation in TensorFlow
Home-page: https://github.com/modichirag/flowpm
Author: Chirag Modi
Author-email: modichirag@berkeley.edu
License: MIT
Keywords: cosmology machine learning
Platform: UNKNOWN
Classifier: Development Status :: 3 - Alpha
Classifier: Intended Audience :: Developers
Classifier: Intended Audience :: Science/Research
Classifier: License :: OSI Approved :: MIT License
Classifier: Topic :: Scientific/Engineering :: Artificial Intelligence
Classifier: Topic :: Scientific/Engineering :: Physics
Provides-Extra: testing
